paperoni/__main__.py
paperoni/commands/command_bibtex.py
paperoni/commands/command_collect.py
paperoni/commands/command_config.py
paperoni/commands/command_html.py
paperoni/commands/command_researcher.py
paperoni/commands/command_search.py
paperoni/commands/default.html
paperoni/commands/interactive.py
paperoni/commands/searchutils.py
paperoni/config.py
paperoni/io.py
paperoni/papers.py
paperoni/query.py
paperoni/researchers.py
paperoni/utils.py
paperoni-0.1.8.dist-info/entry_points.txt
paperoni-0.1.8.dist-info/LICENSE
paperoni-0.1.8.dist-info/WHEEL
paperoni-0.1.8.dist-info/METADATA
paperoni-0.1.8.dist-info/RECORD
