Metadata-Version: 2.1
Name: paperoni
Version: 0.1.8
Summary: Search for scientific papers
Home-page: https://github.com/mila-iqia/paperoni
License: MIT
Author: Olivier Breuleux
Author-email: breuleux@gmail.com
Requires-Python: >=3.7,<4.0
Classifier: License :: OSI Approved :: MIT License
Classifier: Programming Language :: Python :: 3
Classifier: Programming Language :: Python :: 3.7
Classifier: Programming Language :: Python :: 3.8
Requires-Dist: beautifulsoup4 (>=4.9.1,<5.0.0)
Requires-Dist: blessed (>=1.17.9,<2.0.0)
Requires-Dist: coleo (>=0.2.1,<0.3.0)
Requires-Dist: hrepr (>=0.3.1,<0.4.0)
Requires-Dist: requests (>=2.24.0,<3.0.0)
Requires-Dist: tqdm (>=4.48.2,<5.0.0)
Project-URL: Repository, https://github.com/mila-iqia/paperoni
